uiflow_custom_block_generator/__init__.py
uiflow_custom_block_generator/__main__.py
uiflow_custom_block_generator/uiflow_custom_block.py
uiflow_custom_block_generator/uiflow_custom_block_generator.py
uiflow_custom_block_generator/uiflow_custom_block_parser.py
uiflow_custom_block_generator-0.0.5.dist-info/LICENSE
uiflow_custom_block_generator-0.0.5.dist-info/METADATA
uiflow_custom_block_generator-0.0.5.dist-info/WHEEL
uiflow_custom_block_generator-0.0.5.dist-info/top_level.txt
uiflow_custom_block_generator-0.0.5.dist-info/RECORD
