Metadata-Version: 2.1
Name: uiflow-custom-block-generator
Version: 0.0.5
Summary: Generating a custom block file for UiFlow
Home-page: https://github.com/3110/uiflow-custom-block-generator
Author: SAITO Tetsuya
Author-email: saito.tetsuya+github@gmail.com
Project-URL: Bug Tracker, https://github.com/3110/uiflow-custom-block-generator/issues
Classifier: Programming Language :: Python :: 3
Classifier: License :: OSI Approved :: MIT License
Classifier: Operating System :: OS Independent
Requires-Python: >=3.6
License-File: LICENSE
